LICENSE
README.md
setup.py
cfa/__init__.py
cfa/function.py
cfa/main.py
cfa/prompt.py
cfa/url.py
cfa/additionalFiles/__init__.py
cfa/additionalFiles/config.py
cfa/additionalFiles/example.py
cfa/additionalFiles/model.py
cfa/additionalFiles/wsgi.py
create_flask_project.egg-info/PKG-INFO
create_flask_project.egg-info/SOURCES.txt
create_flask_project.egg-info/dependency_links.txt
create_flask_project.egg-info/entry_points.txt
create_flask_project.egg-info/requires.txt
create_flask_project.egg-info/top_level.txt
test/__init__.py
test/test_cli.py